2. MUX/2to1MUX Structural level/mux2to1str.v
module mux2to1str (input sel, input a, input b, output y);
  // 2 to 1 mux at structural level
  // sel=select line, a&b=inputs lines
  wire sel_not, a_nand_sel, b_nand_sel, ab_nand;
  // declaring wires
  // NOT gate inverts select line input
  not u_sel_not (sel_not, sel);
    // NAND gates for selection of inputs a or b
  nand u_a_nand_sel (a_nand_sel, a, sel_not);
    //NAND between input a and inverted select line
  nand u_b_nand_sel (b_nand_sel, b, sel);
    //NAND betwwen input b and select line
  nand u_ab_nand (ab_nand, a_nand_sel, b_nand_sel);
    // Assigning the output of the NOR gate to the output port
  assign y = ab_nand;
endmodule
// test bench file is mux2to1str_tb.v

2. MUX/2to1MUX Structural level/mux2to1str_tb.v
`timescale 1ns / 1ns
`include "mux2to1str.v"
module mux2to1str_tb;
  reg sel;
  reg a;
  reg b;
  wire y;
  //Inputs & Outputs
    mux2to1str uut (.sel(sel), .a(a), .b(b), .y(y));
  
  initial begin
    $dumpfile("mux2to1str.vcd");
    $dumpvars(0, mux2to1str_tb);
        // Test case - sel=0, a=0, b=0
    sel = 0;
    a = 0;
    b = 0;
    #5;
    $display("Test case - sel=0, a=0, b=0: y=%b", y);
    
    // Test case - sel=0, a=0, b=1
    sel = 0;
    a = 0;
    b = 1;
    #5;
    $display("Test case - sel=0, a=0, b=1: y=%b", y);
    
    // Test case - sel=0, a=1, b=0
    sel = 0;
    a = 1;
    b = 0;
    #5;
    $display("Test case - sel=0, a=1, b=0: y=%b", y);
    
    // Test case - sel=0, a=1, b=1
    sel = 0;
    a = 1;
    b = 1;
    #5;
    $display("Test case - sel=0, a=1, b=1: y=%b", y);
    
    // Test case - sel=1, a=0, b=0
    sel = 1;
    a = 0;
    b = 0;
    #5;
    $display("Test case - sel=1, a=0, b=0: y=%b", y);
    
    // Test case - sel=1, a=0, b=1
    sel = 1;
    a = 0;
    b = 1;
    #5;
    $display("Test case - sel=1, a=0, b=1: y=%b", y);
    
    // Test case - sel=1, a=1, b=0
    sel = 1;
    a = 1;
    b = 0;
    #5;
    $display("Test case - sel=1, a=1, b=0: y=%b", y);
    
    // Test case - sel=1, a=1, b=1
    sel = 1;
    a = 1;
    b = 1;
    #5;
    $display("Test case - sel=1, a=1, b=1: y=%b", y);
    
    $finish;
  end
endmodule

2. MUX/2to1MUX Structural level/mux2to1str.vcd
$date
	Thu May 04 11:30:03 2023
$end
$version
	Icarus Verilog
$end
$timescale
	1ns
$end
$scope module mux2to1str_tb $end
$var wire 1 ! y $end
$var reg 1 " a $end
$var reg 1 # b $end
$var reg 1 $ sel $end
$scope module uut $end
$var wire 1 " a $end
$var wire 1 % a_nand_sel $end
$var wire 1 & ab_nand $end
$var wire 1 # b $end
$var wire 1 ' b_nand_sel $end
$var wire 1 $ sel $end
$var wire 1 ( sel_not $end
$var wire 1 ! y $end
$upscope $end
$upscope $end
$enddefinitions $end
$comment Show the parameter values. $end
$dumpall
$end
#0
$dumpvars
1(
1'
0&
1%
0$
0#
0"
0!
$end
#5
1#
#10
1!
1&
0%
0#
1"
#15
1#
#20
0!
0&
1%
0(
0#
0"
1$
#25
1!
1&
0'
1#
#30
0!
0&
1'
0#
1"
#35
1!
1&
0'
1#
