3. JK FF/JK Flipflop Counter/jkff_upcounter.v
module jkff_upcounter(clk,reset,q);
  input clk,reset;
  output [3:0] q;
  wire j2,j3,q0_bar;
//input & output initialization
   
  jkff ff0(.j(1'b1), .k(1'b1), .clk(clk), .rst(reset), .q(q[0]));
  jkff ff1(.j(q[0]), .k(q[0]), .clk(clk), .rst(reset), .q(q[1]));
  and(j2,q[1],q[0]);
  jkff ff2(.j(j2), .k(j2), .clk(clk), .rst(reset), .q(q[2]));
  and(j3,q[2],q[1],q[0]);
  jkff ff3(.j(j3), .k(j3), .clk(clk), .rst(reset), .q(q[3]));
  //interconnecting JK flipflops and logic gates using wires
endmodule

module jkff(j,k,clk,rst,q);
    input j,k,clk,rst;
    output reg q;
    reg qbar;
    
    //positive edge triggered JK flipflop
    always@(posedge clk)
    begin
        if(rst) begin
        q<=0;
        qbar <=1; end
        else
        begin
    case({j,k})
        2'b00:begin
            q<=q;
            qbar<=qbar;
        end
        2'b01:begin
            q<= 0;
            qbar<=1;
        end
        2'b10:begin
            q<=1;
            qbar<=0;
        end

        2'b11:begin
            q<= ~q;
            qbar<=~qbar;end
    endcase
        end
    end     
endmodule

3. JK FF/JK Flipflop Counter/jkff_upcounter_tb.v
`include "jkff_upcounter.v"
module jkff_upcounter_tb;
  reg clk, reset;
  integer i;
  wire [3:0] q;

  jkff_upcounter counter(.clk(clk), .reset(reset), .q(q));

  initial begin
    clk = 0;
    for (i=1;i<66;i=i+1)begin
   #2 clk=~clk; 
    end
  end

  initial begin
    $dumpfile("jkff_upcounter.vcd");
    $dumpvars(0, jkff_upcounter_tb);
  end

  initial 
    $monitor("simtime=%g,clk=%b,reset=%b,count=%b%b%b%b",$time,clk,reset,q[3],q[2],q[1],q[0]);
initial 
begin
  reset=1;
 #10 reset=0; 
  #150 reset=1;
end

endmodule

3. JK FF/JK Flipflop Counter/jkff_upcounter.vcd
$date
	Thu May 04 13:32:32 2023
$end
$version
	Icarus Verilog
$end
$timescale
	1s
$end
$scope module jkff_upcounter_tb $end
$var wire 4 ! q [3:0] $end
$var reg 1 " clk $end
$var reg 1 # reset $end
$var integer 32 $ i [31:0] $end
$scope module counter $end
$var wire 1 " clk $end
$var wire 1 % j2 $end
$var wire 1 & j3 $end
$var wire 1 # reset $end
$var wire 4 ' q [3:0] $end
$scope module ff0 $end
$var wire 1 " clk $end
$var wire 1 ( j $end
$var wire 1 ) k $end
$var wire 1 # rst $end
$var reg 1 * q $end
$var reg 1 + qbar $end
$upscope $end
$scope module ff1 $end
$var wire 1 " clk $end
$var wire 1 , j $end
$var wire 1 - k $end
$var wire 1 # rst $end
$var reg 1 . q $end
$var reg 1 / qbar $end
$upscope $end
$scope module ff2 $end
$var wire 1 " clk $end
$var wire 1 % j $end
$var wire 1 % k $end
$var wire 1 # rst $end
$var reg 1 0 q $end
$var reg 1 1 qbar $end
$upscope $end
$scope module ff3 $end
$var wire 1 " clk $end
$var wire 1 & j $end
$var wire 1 & k $end
$var wire 1 # rst $end
$var reg 1 2 q $end
$var reg 1 3 qbar $end
$upscope $end
$upscope $end
$upscope $end
$enddefinitions $end
$comment Show the parameter values. $end
$dumpall
$end
#0
$dumpvars
x3
x2
x1
x0
x/
x.
x-
x,
x+
x*
1)
1(
bx '
x&
x%
b1 $
1#
0"
bx !
$end
#2
0%
0&
0-
0,
1+
0*
1/
0.
11
00
13
b0 !
b0 '
02
b10 $
1"
#4
b11 $
0"
#6
b100 $
1"
#8
b101 $
0"
#10
1-
1,
0+
b1 !
b1 '
1*
b110 $
1"
0#
#12
b111 $
0"
#14
0-
0,
0/
1.
1+
b10 !
b10 '
0*
b1000 $
1"
#16
b1001 $
0"
#18
1%
1-
1,
0+
b11 !
b11 '
1*
b1010 $
1"
#20
b1011 $
0"
#22
0%
0-
0,
01
10
1/
0.
1+
b100 !
b100 '
0*
b1100 $
1"
#24
b1101 $
0"
#26
1-
1,
0+
b101 !
b101 '
1*
b1110 $
1"
#28
b1111 $
0"
#30
0-
0,
0/
1.
1+
b110 !
b110 '
0*
b10000 $
1"
#32
b10001 $
0"
#34
1&
1%
1-
1,
0+
b111 !
b111 '
1*
b10010 $
1"
#36
b10011 $
0"
#38
0&
0%
0-
0,
03
12
11
00
1/
0.
1+
b1000 !
b1000 '
0*
b10100 $
1"
#40
b10101 $
0"
#42
1-
1,
0+
b1001 !
b1001 '
1*
b10110 $
1"
#44
b10111 $
0"
#46
0-
0,
0/
1.
1+
b1010 !
b1010 '
0*
b11000 $
1"
#48
b11001 $
0"
#50
1%
1-
1,
0+
b1011 !
b1011 '
1*
b11010 $
1"
#52
b11011 $
0"
#54
0%
0-
0,
01
10
1/
0.
1+
b1100 !
b1100 '
0*
b11100 $
1"
#56
b11101 $
0"
#58
1-
1,
0+
b1101 !
b1101 '
1*
b11110 $
1"
#60
b11111 $
0"
#62
0-
0,
0/
1.
1+
b1110 !
b1110 '
0*
b100000 $
1"
#64
b100001 $
0"
#66
1&
1%
1-
1,
0+
b1111 !
b1111 '
1*
b100010 $
1"
#68
b100011 $
0"
#70
0&
0%
0-
0,
13
02
11
00
1/
0.
1+
b0 !
b0 '
0*
b100100 $
1"
#72
b100101 $
0"
#74
1-
1,
0+
b1 !
b1 '
1*
b100110 $
1"
#76
b100111 $
0"
#78
0-
0,
0/
1.
1+
b10 !
b10 '
0*
b101000 $
1"
#80
b101001 $
0"
#82
1%
1-
1,
0+
b11 !
b11 '
1*
b101010 $
1"
#84
b101011 $
0"
#86
0%
0-
0,
01
10
1/
0.
1+
b100 !
b100 '
0*
b101100 $
1"
#88
b101101 $
0"
#90
1-
1,
0+
b101 !
b101 '
1*
b101110 $
1"
#92
b101111 $
0"
#94
0-
0,
0/
1.
1+
b110 !
b110 '
0*
b110000 $
1"
#96
b110001 $
0"
#98
1&
1%
1-
1,
0+
b111 !
b111 '
1*
b110010 $
1"
#100
b110011 $
0"
#102
0&
0%
0-
0,
03
12
11
00
1/
0.
1+
b1000 !
b1000 '
0*
b110100 $
1"
#104
b110101 $
0"
#106
1-
1,
0+
b1001 !
b1001 '
1*
b110110 $
1"
#108
b110111 $
0"
#110
0-
0,
0/
1.
1+
b1010 !
b1010 '
0*
b111000 $
1"
#112
b111001 $
0"
#114
1%
1-
1,
0+
b1011 !
b1011 '
1*
b111010 $
1"
#116
b111011 $
0"
#118
0%
0-
0,
01
10
1/
0.
1+
b1100 !
b1100 '
0*
b111100 $
1"
#120
b111101 $
0"
#122
1-
1,
0+
b1101 !
b1101 '
1*
b111110 $
1"
#124
b111111 $
0"
#126
0-
0,
0/
1.
1+
b1110 !
b1110 '
0*
b1000000 $
1"
#128
b1000001 $
0"
#130
1&
1%
1-
1,
0+
b1111 !
b1111 '
1*
b1000010 $
1"
#160
1#
