2. MUX/32to1MUX Structural level/mux32to1str.v
module mux32to1str (input [4:0] sel, input [31:0] a, output [0:0] y);

  //16 MUX in first level
  mux2to1 u_mux0 (.sel(sel[0]), .a(a[0]), .b(a[1]), .y(w0));
  mux2to1 u_mux1 (.sel(sel[0]), .a(a[2]), .b(a[3]), .y(w1));
  mux2to1 u_mux2 (.sel(sel[0]), .a(a[4]), .b(a[5]), .y(w2));
  mux2to1 u_mux3 (.sel(sel[0]), .a(a[6]), .b(a[7]), .y(w3));
  mux2to1 u_mux4 (.sel(sel[0]), .a(a[8]), .b(a[9]), .y(w4));
  mux2to1 u_mux5 (.sel(sel[0]), .a(a[10]), .b(a[11]), .y(w5));
  mux2to1 u_mux6 (.sel(sel[0]), .a(a[12]), .b(a[13]), .y(w6));
  mux2to1 u_mux7 (.sel(sel[0]), .a(a[14]), .b(a[15]), .y(w7));
  mux2to1 u_mux8 (.sel(sel[0]), .a(a[16]), .b(a[17]), .y(w8));
  mux2to1 u_mux9 (.sel(sel[0]), .a(a[18]), .b(a[19]), .y(w9));
  mux2to1 u_mux10 (.sel(sel[0]), .a(a[20]), .b(a[21]), .y(w10));
  mux2to1 u_mux11 (.sel(sel[0]), .a(a[22]), .b(a[23]), .y(w11));
  mux2to1 u_mux12 (.sel(sel[0]), .a(a[24]), .b(a[25]), .y(w12));
  mux2to1 u_mux13 (.sel(sel[0]), .a(a[26]), .b(a[27]), .y(w13));
  mux2to1 u_mux14 (.sel(sel[0]), .a(a[28]), .b(a[29]), .y(w14));
  mux2to1 u_mux15 (.sel(sel[0]), .a(a[30]), .b(a[31]), .y(w15));

  // 8 MUX in 2nd level
  mux2to1 u_mux16 (.sel(sel[1]), .a(w0), .b(w1), .y(w16));
  mux2to1 u_mux17 (.sel(sel[1]), .a(w2), .b(w3), .y(w17));
  mux2to1 u_mux18 (.sel(sel[1]), .a(w4), .b(w5), .y(w18));
  mux2to1 u_mux19 (.sel(sel[1]), .a(w6), .b(w7), .y(w19));
  mux2to1 u_mux20 (.sel(sel[1]), .a(w8), .b(w9), .y(w20));
  mux2to1 u_mux21 (.sel(sel[1]), .a(w10), .b(w11), .y(w21));
  mux2to1 u_mux22 (.sel(sel[1]), .a(w12), .b(w13), .y(w22));
  mux2to1 u_mux23 (.sel(sel[1]), .a(w14), .b(w15), .y(w23));
  
  // 4 MUX in 3rd level
  mux2to1 u_mux24 (.sel(sel[2]), .a(w16), .b(w17), .y(w24));
  mux2to1 u_mux25 (.sel(sel[2]), .a(w18), .b(w19), .y(w25));
  mux2to1 u_mux26 (.sel(sel[2]), .a(w20), .b(w21), .y(w26));
  mux2to1 u_mux27 (.sel(sel[2]), .a(w22), .b(w23), .y(w27));

  // 2 MUX in 4th level
  mux2to1 u_mux28 (.sel(sel[3]), .a(w24), .b(w25), .y(w28));
  mux2to1 u_mux29 (.sel(sel[3]), .a(w26), .b(w27), .y(w29));

  // 1 MUX in 5th level
  mux2to1 u_mux30 (.sel(sel[4]), .a(w28), .b(w29), .y(y));
  
endmodule
module mux2to1 (input sel, input a, input b, output y);
    reg y;
    always@(*)begin
        if(sel==0)
        y=a;
        else
        y=b;
    end
endmodule

2. MUX/32to1MUX Structural level/mux32to1str_tb.v
`include "mux32to1str.v"
module mux32to1str_tb;

  mux32to1str dut (
    .sel(sel),
    .a(a),
    .y(y)
  );

  // Inputs
  reg [4:0] sel;
  reg [31:0] a;
  
  // Output
  wire [0:0] y;
  
  // Initialize inputs
  initial begin
    $dumpfile("mux32x1str.vcd");
    $dumpvars(0, mux32to1str_tb);
    // Test case 1
    sel = 5'b00000;
    a = 32'b00000000000000000000000000000001;
    #5;
    $display("Test case 1: sel=%b, a=%b, y=%b", sel, a, y);

    // Test case 2
    sel = 5'b00001;
    a = 32'b00000000000000000000000000000010;
    #5;
    $display("Test case 2: sel=%b, a=%b, y=%b", sel, a, y);

    // Test case 3
    sel = 5'b00010;
    a = 32'b00000000000000000000000000000100;
    #5;
    $display("Test case 3: sel=%b, a=%b, y=%b", sel, a, y);

    // Test case 4
    sel = 5'b00011;
    a = 32'b00000000000000000000000000001000;
    #5;
    $display("Test case 4: sel=%b, a=%b, y=%b", sel, a, y);

    // Test case 5
    sel = 5'b11111;
    a = 32'b10000000000000000000000000000000;
    #5;
    $display("Test case 5: sel=%b, a=%b, y=%b", sel, a, y);
    
    // Test case 6
    sel = 5'b11110;
    a = 32'b01000000000000000000000000000000;
    #5;
    $display("Test case 6: sel=%b, a=%b, y=%b", sel, a, y);

    // Test case 7
    sel = 5'b11101;
    a = 32'b00100000000000000000000000000000;
    #5;
    $display("Test case 7: sel=%b, a=%b, y=%b", sel, a, y);

    // Test case 8
    sel = 5'b11100;
    a = 32'b00010000000000000000000000000000;
    #5;
    $display("Test case 8: sel=%b, a=%b, y=%b", sel, a, y);

    $finish;
  end

endmodule

2. MUX/32to1MUX Structural level/mux32x1str.vcd
$date
	Thu May 04 12:45:26 2023
$end
$version
	Icarus Verilog
$end
$timescale
	1s
$end
$scope module mux32to1str_tb $end
$var wire 1 ! y $end
$var reg 32 " a [31:0] $end
$var reg 5 # sel [4:0] $end
$scope module dut $end
$var wire 32 $ a [31:0] $end
$var wire 5 % sel [4:0] $end
$var wire 1 ! y $end
$var wire 1 & w9 $end
$var wire 1 ' w8 $end
$var wire 1 ( w7 $end
$var wire 1 ) w6 $end
$var wire 1 * w5 $end
$var wire 1 + w4 $end
$var wire 1 , w3 $end
$var wire 1 - w29 $end
$var wire 1 . w28 $end
$var wire 1 / w27 $end
$var wire 1 0 w26 $end
$var wire 1 1 w25 $end
$var wire 1 2 w24 $end
$var wire 1 3 w23 $end
$var wire 1 4 w22 $end
$var wire 1 5 w21 $end
$var wire 1 6 w20 $end
$var wire 1 7 w2 $end
$var wire 1 8 w19 $end
$var wire 1 9 w18 $end
$var wire 1 : w17 $end
$var wire 1 ; w16 $end
$var wire 1 < w15 $end
$var wire 1 = w14 $end
$var wire 1 > w13 $end
$var wire 1 ? w12 $end
$var wire 1 @ w11 $end
$var wire 1 A w10 $end
$var wire 1 B w1 $end
$var wire 1 C w0 $end
$scope module u_mux0 $end
$var wire 1 D a $end
$var wire 1 E b $end
$var wire 1 F sel $end
$var reg 1 C y $end
$upscope $end
$scope module u_mux1 $end
$var wire 1 G a $end
$var wire 1 H b $end
$var wire 1 I sel $end
$var reg 1 B y $end
$upscope $end
$scope module u_mux10 $end
$var wire 1 J a $end
$var wire 1 K b $end
$var wire 1 L sel $end
$var reg 1 A y $end
$upscope $end
$scope module u_mux11 $end
$var wire 1 M a $end
$var wire 1 N b $end
$var wire 1 O sel $end
$var reg 1 @ y $end
$upscope $end
$scope module u_mux12 $end
$var wire 1 P a $end
$var wire 1 Q b $end
$var wire 1 R sel $end
$var reg 1 ? y $end
$upscope $end
$scope module u_mux13 $end
$var wire 1 S a $end
$var wire 1 T b $end
$var wire 1 U sel $end
$var reg 1 > y $end
$upscope $end
$scope module u_mux14 $end
$var wire 1 V a $end
$var wire 1 W b $end
$var wire 1 X sel $end
$var reg 1 = y $end
$upscope $end
$scope module u_mux15 $end
$var wire 1 Y a $end
$var wire 1 Z b $end
$var wire 1 [ sel $end
$var reg 1 < y $end
$upscope $end
$scope module u_mux16 $end
$var wire 1 C a $end
$var wire 1 B b $end
$var wire 1 \ sel $end
$var reg 1 ; y $end
$upscope $end
$scope module u_mux17 $end
$var wire 1 ] sel $end
$var wire 1 , b $end
$var wire 1 7 a $end
$var reg 1 : y $end
$upscope $end
$scope module u_mux18 $end
$var wire 1 ^ sel $end
$var wire 1 * b $end
$var wire 1 + a $end
$var reg 1 9 y $end
$upscope $end
$scope module u_mux19 $end
$var wire 1 _ sel $end
$var wire 1 ( b $end
$var wire 1 ) a $end
$var reg 1 8 y $end
$upscope $end
$scope module u_mux2 $end
$var wire 1 ` a $end
$var wire 1 a b $end
$var wire 1 b sel $end
$var reg 1 7 y $end
$upscope $end
$scope module u_mux20 $end
$var wire 1 c sel $end
$var wire 1 & b $end
$var wire 1 ' a $end
$var reg 1 6 y $end
$upscope $end
$scope module u_mux21 $end
$var wire 1 A a $end
$var wire 1 @ b $end
$var wire 1 d sel $end
$var reg 1 5 y $end
$upscope $end
$scope module u_mux22 $end
$var wire 1 ? a $end
$var wire 1 > b $end
$var wire 1 e sel $end
$var reg 1 4 y $end
$upscope $end
$scope module u_mux23 $end
$var wire 1 = a $end
$var wire 1 < b $end
$var wire 1 f sel $end
$var reg 1 3 y $end
$upscope $end
$scope module u_mux24 $end
$var wire 1 ; a $end
$var wire 1 : b $end
$var wire 1 g sel $end
$var reg 1 2 y $end
$upscope $end
$scope module u_mux25 $end
$var wire 1 9 a $end
$var wire 1 8 b $end
$var wire 1 h sel $end
$var reg 1 1 y $end
$upscope $end
$scope module u_mux26 $end
$var wire 1 6 a $end
$var wire 1 5 b $end
$var wire 1 i sel $end
$var reg 1 0 y $end
$upscope $end
$scope module u_mux27 $end
$var wire 1 4 a $end
$var wire 1 3 b $end
$var wire 1 j sel $end
$var reg 1 / y $end
$upscope $end
$scope module u_mux28 $end
$var wire 1 2 a $end
$var wire 1 1 b $end
$var wire 1 k sel $end
$var reg 1 . y $end
$upscope $end
$scope module u_mux29 $end
$var wire 1 0 a $end
$var wire 1 / b $end
$var wire 1 l sel $end
$var reg 1 - y $end
$upscope $end
$scope module u_mux3 $end
$var wire 1 m a $end
$var wire 1 n b $end
$var wire 1 o sel $end
$var reg 1 , y $end
$upscope $end
$scope module u_mux30 $end
$var wire 1 . a $end
$var wire 1 - b $end
$var wire 1 p sel $end
$var reg 1 ! y $end
$upscope $end
$scope module u_mux4 $end
$var wire 1 q a $end
$var wire 1 r b $end
$var wire 1 s sel $end
$var reg 1 + y $end
$upscope $end
$scope module u_mux5 $end
$var wire 1 t a $end
$var wire 1 u b $end
$var wire 1 v sel $end
$var reg 1 * y $end
$upscope $end
$scope module u_mux6 $end
$var wire 1 w a $end
$var wire 1 x b $end
$var wire 1 y sel $end
$var reg 1 ) y $end
$upscope $end
$scope module u_mux7 $end
$var wire 1 z a $end
$var wire 1 { b $end
$var wire 1 | sel $end
$var reg 1 ( y $end
$upscope $end
$scope module u_mux8 $end
$var wire 1 } a $end
$var wire 1 ~ b $end
$var wire 1 !" sel $end
$var reg 1 ' y $end
$upscope $end
$scope module u_mux9 $end
$var wire 1 "" a $end
$var wire 1 #" b $end
$var wire 1 $" sel $end
$var reg 1 & y $end
$upscope $end
$upscope $end
$upscope $end
$enddefinitions $end
$comment Show the parameter values. $end
$dumpall
$end
#0
$dumpvars
0$"
0#"
0""
0!"
0~
0}
0|
0{
0z
0y
0x
0w
0v
0u
0t
0s
0r
0q
0p
0o
0n
0m
0l
0k
0j
0i
0h
0g
0f
0e
0d
0c
0b
0a
0`
0_
0^
0]
0\
0[
0Z
0Y
0X
0W
0V
0U
0T
0S
0R
0Q
0P
0O
0N
0M
0L
0K
0J
0I
0H
0G
0F
0E
1D
1C
0B
0A
0@
0?
0>
0=
0<
1;
0:
09
08
07
06
05
04
03
12
01
00
0/
1.
0-
0,
0+
0*
0)
0(
0'
0&
b0 %
b1 $
b0 #
b1 "
1!
$end
#5
0D
1E
1F
1I
1b
1o
1s
1v
1y
1|
1!"
1$"
1L
1O
1R
1U
1X
1[
b10 "
b10 $
b1 #
b1 %
#10
1!
1.
12
0C
1B
1;
0E
1G
0F
0I
0b
0o
0s
0v
0y
0|
0!"
0$"
0L
0O
0R
0U
0X
0[
1\
1]
1^
1_
1c
1d
1e
1f
b100 "
b100 $
b10 #
b10 %
#15
0G
1H
1F
1I
1b
1o
1s
1v
1y
1|
1!"
1$"
1L
1O
1R
1U
1X
1[
b1000 "
b1000 $
b11 #
b11 %
#20
1-
1/
0;
13
0B
1<
02
0.
1!
0H
1Z
1g
1h
1i
1j
1k
1l
1p
b10000000000000000000000000000000 "
b10000000000000000000000000000000 $
b11111 #
b11111 %
#25
1Y
0Z
0F
0I
0b
0o
0s
0v
0y
0|
0!"
0$"
0L
0O
0R
0U
0X
0[
b1000000000000000000000000000000 "
b1000000000000000000000000000000 $
b11110 #
b11110 %
#30
1!
1-
1/
1=
0<
13
1W
0Y
1F
1I
1b
1o
1s
1v
1y
1|
1!"
1$"
1L
1O
1R
1U
1X
1[
0\
0]
0^
0_
0c
0d
0e
0f
b100000000000000000000000000000 "
b100000000000000000000000000000 $
b11101 #
b11101 %
#35
1V
0W
0F
0I
0b
0o
0s
0v
0y
0|
0!"
0$"
0L
0O
0R
0U
0X
0[
b10000000000000000000000000000 "
b10000000000000000000000000000 $
b11100 #
b11100 %
