2. MUX/2to1MUX Behavioral level/mux2to1beh.v
module mux2to1beh (input wire sel, input wire a, input wire b, output reg out);
// inputs declaration
    initial begin
    $dumpfile("mux2to1beh.vcd");
    $dumpvars(0, mux2to1beh_tb);
    end
    always @(sel, a, b)  //structural logic for 2to1mux
        if(sel)
            out = b;
        else
            out = a;
endmodule

2. MUX/2to1MUX Behavioral level/mux2to1beh_tb.v
`timescale 1ns/1ns // Set timescale for simulation
`include "mux2to1beh.v"

module mux2to1beh_tb;

  // Inputs
  reg sel;
  reg a;
  reg b;
  
  // Outputs
  wire out;

  mux2to1beh uut(
    .sel(sel),
    .a(a),
    .b(b),
    .out(out)
  );
  
  initial begin
        // Test case - sel=0, a=0, b=0
    sel = 0;
    a = 0;
    b = 0;
    #5;
    $display("Test case - sel=0, a=0, b=0: out=%b", out);
    
    // Test case - sel=0, a=0, b=1
    sel = 0;
    a = 0;
    b = 1;
    #5;
    $display("Test case - sel=0, a=0, b=1: out=%b", out);
    
    // Test case - sel=0, a=1, b=0
    sel = 0;
    a = 1;
    b = 0;
    #5;
    $display("Test case - sel=0, a=1, b=0: out=%b", out);
    
    // Test case - sel=0, a=1, b=1
    sel = 0;
    a = 1;
    b = 1;
    #5;
    $display("Test case - sel=0, a=1, b=1: out=%b", out);
    
    // Test case - sel=1, a=0, b=0
    sel = 1;
    a = 0;
    b = 0;
    #5;
    $display("Test case - sel=1, a=0, b=0: out=%b", out);
    
    // Test case - sel=1, a=0, b=1
    sel = 1;
    a = 0;
    b = 1;
    #5;
    $display("Test case - sel=1, a=0, b=1: out=%b", out);
    
    // Test case - sel=1, a=1, b=0
    sel = 1;
    a = 1;
    b = 0;
    #5;
    $display("Test case - sel=1, a=1, b=0: out=%b", out);
    
    // Test case - sel=1, a=1, b=1
    sel = 1;
    a = 1;
    b = 1;
    #5;
    $display("Test case - sel=1, a=1, b=1: out=%b", out);
    
    $finish;
  end
  
endmodule

2. MUX/2to1MUX Behavioral level/mux2to1beh.vcd
$date
	Thu May 04 11:56:20 2023
$end
$version
	Icarus Verilog
$end
$timescale
	1ns
$end
$scope module mux2to1beh_tb $end
$var wire 1 ! out $end
$var reg 1 " a $end
$var reg 1 # b $end
$var reg 1 $ sel $end
$scope module uut $end
$var wire 1 " a $end
$var wire 1 # b $end
$var wire 1 $ sel $end
$var reg 1 ! out $end
$upscope $end
$upscope $end
$enddefinitions $end
$comment Show the parameter values. $end
$dumpall
$end
#0
$dumpvars
0$
0#
0"
0!
$end
#5
1#
#10
1!
0#
1"
#15
1#
#20
0!
0#
0"
1$
#25
1!
1#
#30
0!
0#
1"
#35
1!
1#
