3. JK FF/JK Flipflop Behavioral Level/jkffbeh.v
module jkffbeh(jk,clk,q,qbar);
    input [1:0] jk;
    input clk;
    output q,qbar;
    reg q,qbar;

    always@(negedge clk)
    begin
    case(jk)
        2'b00:
            q= q;

        2'b01:
            q= 0;

        2'b10:
            q=1;

        2'b11:
            q= ~q;
    endcase

    qbar = ~q;
    
    end 
endmodule

3. JK FF/JK Flipflop Behavioral Level/jkffbeh_tb.v
`timescale 1ns / 1ns
`include "jkffbeh.v"

module jkffbeh_tb;
    reg [1:0] jk;
    reg clk;
    integer i;
    wire q,qbar;
    jkffbeh j1(jk,clk,q,qbar);
    initial 
    begin
    $display("jkffbeh.vcd");
    $monitor("%b  %b %b \t %b %b",jk[1],jk[1],jk[0],clk,q,qbar);
    $dumpfile("jkffbeh_tb.vcd");
    $dumpvars(0,jkffbeh_tb);

        jk = 2'b00;
        #10

        jk = 2'b01;
        #10

        jk = 2'b10;
        #10

        jk = 2'b11;
        #10
    $finish;
    end
    initial
    begin
        clk = 0;
        for(i=0;i<20;i=i+1)
            #5 clk = ~clk;
    end 
endmodule

3. JK FF/JK Flipflop Behavioral Level/jkffbeh_tb.vcd
$date
	Thu May 04 13:20:52 2023
$end
$version
	Icarus Verilog
$end
$timescale
	1ns
$end
$scope module jkffbeh_tb $end
$var wire 1 ! qbar $end
$var wire 1 " q $end
$var reg 1 # clk $end
$var reg 2 $ jk [1:0] $end
$var integer 32 % i [31:0] $end
$scope module j1 $end
$var wire 1 # clk $end
$var wire 2 & jk [1:0] $end
$var reg 1 " q $end
$var reg 1 ! qbar $end
$upscope $end
$upscope $end
$enddefinitions $end
$comment Show the parameter values. $end
$dumpall
$end
#0
$dumpvars
b0 &
b0 %
b0 $
0#
x"
x!
$end
#5
b1 %
1#
#10
1!
0"
b10 %
0#
b1 $
b1 &
#15
b11 %
1#
#20
0!
1"
b100 %
0#
b10 $
b10 &
#25
b101 %
1#
#30
1!
0"
b110 %
0#
b11 $
b11 &
#35
b111 %
1#
#40
0!
1"
b1000 %
0#
